Workbook

Sheet Lançamentos
A1: Data | B1: Descrição | C1: Tipo | D1: Categoria | E1: Valor (R$) | F1: Mês
A2: 46266 | B2: Salário | C2: Entrada | D2: Outros | E2: 3200 | F2: =IF(A2="","",DATE(YEAR(A2),MONTH(A2),1))
A3: 46267 | B3: Aluguel | C3: Saída | D3: Moradia | E3: 900 | F3: =IF(A3="","",DATE(YEAR(A3),MONTH(A3),1))
A4: 46270 | B4: Supermercado | C4: Saída | D4: Mercado | E4: 520.4 | F4: =IF(A4="","",DATE(YEAR(A4),MONTH(A4),1))
A5: 46273 | B5: Gasolina | C5: Saída | D5: Transporte | E5: 180 | F5: =IF(A5="","",DATE(YEAR(A5),MONTH(A5),1))
A6: 46277 | B6: Farmácia | C6: Saída | D6: Saúde | E6: 76.9 | F6: =IF(A6="","",DATE(YEAR(A6),MONTH(A6),1))
A7: 46280 | B7: Cinema | C7: Saída | D7: Lazer | E7: 60 | F7: =IF(A7="","",DATE(YEAR(A7),MONTH(A7),1))
A8: 46285 | B8: Curso online | C8: Saída | D8: Educação | E8: 97 | F8: =IF(A8="","",DATE(YEAR(A8),MONTH(A8),1))
A9: 46290 | B9: Freela | C9: Entrada | D9: Outros | E9: 450 | F9: =IF(A9="","",DATE(YEAR(A9),MONTH(A9),1))
A10: 46296 | B10: Salário | C10: Entrada | D10: Outros | E10: 3200 | F10: =IF(A10="","",DATE(YEAR(A10),MONTH(A10),1))
A11: 46297 | B11: Aluguel | C11: Saída | D11: Moradia | E11: 900 | F11: =IF(A11="","",DATE(YEAR(A11),MONTH(A11),1))
A12: 46301 | B12: Supermercado | C12: Saída | D12: Mercado | E12: 610.15 | F12: =IF(A12="","",DATE(YEAR(A12),MONTH(A12),1))
A13: 46304 | B13: Ônibus | C13: Saída | D13: Transporte | E13: 95 | F13: =IF(A13="","",DATE(YEAR(A13),MONTH(A13),1))
F14: =IF(A14="","",DATE(YEAR(A14),MONTH(A14),1))
F15: =IF(A15="","",DATE(YEAR(A15),MONTH(A15),1))
F16: =IF(A16="","",DATE(YEAR(A16),MONTH(A16),1))
F17: =IF(A17="","",DATE(YEAR(A17),MONTH(A17),1))
F18: =IF(A18="","",DATE(YEAR(A18),MONTH(A18),1))
F19: =IF(A19="","",DATE(YEAR(A19),MONTH(A19),1))
F20: =IF(A20="","",DATE(YEAR(A20),MONTH(A20),1))
F21: =IF(A21="","",DATE(YEAR(A21),MONTH(A21),1))
F22: =IF(A22="","",DATE(YEAR(A22),MONTH(A22),1))
F23: =IF(A23="","",DATE(YEAR(A23),MONTH(A23),1))
F24: =IF(A24="","",DATE(YEAR(A24),MONTH(A24),1))
F25: =IF(A25="","",DATE(YEAR(A25),MONTH(A25),1))
... F200: =IF(A200="","",DATE(YEAR(A200),MONTH(A200),1))

Sheet Resumo
A1: Resumo financeiro
A2: Mês de referência | B2: 46266 | C2: (troque o mês aqui)
A3: Total de entradas | B3: =SUMIFS(Lançamentos!E:E,Lançamentos!C:C,"Entrada",Lançamentos!F:F,B2)
A4: Total de saídas | B4: =SUMIFS(Lançamentos!E:E,Lançamentos!C:C,"Saída",Lançamentos!F:F,B2)
A5: Saldo | B5: =B3-B4
A7: Categoria | B7: Gasto | C7: Orçamento | D7: % usado
A8: Moradia | B8: =SUMIFS(Lançamentos!E:E,Lançamentos!C:C,"Saída",Lançamentos!D:D,A8,Lançamentos!F:F,$B$2) | C8: 1000 | D8: =IF(C8=0,0,B8/C8)
A9: Mercado | B9: =SUMIFS(Lançamentos!E:E,Lançamentos!C:C,"Saída",Lançamentos!D:D,A9,Lançamentos!F:F,$B$2) | C9: 600 | D9: =IF(C9=0,0,B9/C9)
A10: Transporte | B10: =SUMIFS(Lançamentos!E:E,Lançamentos!C:C,"Saída",Lançamentos!D:D,A10,Lançamentos!F:F,$B$2) | C10: 250 | D10: =IF(C10=0,0,B10/C10)
A11: Saúde | B11: =SUMIFS(Lançamentos!E:E,Lançamentos!C:C,"Saída",Lançamentos!D:D,A11,Lançamentos!F:F,$B$2) | C11: 150 | D11: =IF(C11=0,0,B11/C11)
A12: Lazer | B12: =SUMIFS(Lançamentos!E:E,Lançamentos!C:C,"Saída",Lançamentos!D:D,A12,Lançamentos!F:F,$B$2) | C12: 150 | D12: =IF(C12=0,0,B12/C12)
A13: Educação | B13: =SUMIFS(Lançamentos!E:E,Lançamentos!C:C,"Saída",Lançamentos!D:D,A13,Lançamentos!F:F,$B$2) | C13: 120 | D13: =IF(C13=0,0,B13/C13)
A14: Outros | B14: =SUMIFS(Lançamentos!E:E,Lançamentos!C:C,"Saída",Lançamentos!D:D,A14,Lançamentos!F:F,$B$2) | C14: 200 | D14: =IF(C14=0,0,B14/C14)
